minecode_pipeline/README.rst
minecode_pipeline/__init__.py
minecode_pipeline/miners/__init__.py
minecode_pipeline/miners/pypi.py
minecode_pipeline/pipelines/__init__.py
minecode_pipeline/pipelines/mine_pypi.py
minecode_pipeline/pipes/__init__.py
minecode_pipeline/pipes/pypi.py
minecode_pipeline/utils.py
minecode_pipeline-0.0.1b1.dist-info/entry_points.txt
minecode_pipeline-0.0.1b1.dist-info/WHEEL
minecode_pipeline-0.0.1b1.dist-info/METADATA
minecode_pipeline-0.0.1b1.dist-info/NOTICE
minecode_pipeline-0.0.1b1.dist-info/apache-2.0.LICENSE
minecode_pipeline-0.0.1b1.dist-info/RECORD
