Metadata-Version: 2.1
Name: minecode_pipeline
Version: 0.0.1b1
Summary: A library for mining packageURLs and package metadata from ecosystem repositories.
Keywords: purl,Package-URL,open source,package,sca,scan,index,federated,data
Author-email: "AboutCode, nexB Inc. and others" <info@aboutcode.org>
Requires-Python: >=3.10
Classifier: Development Status :: 5 - Production/Stable
Classifier: Intended Audience :: Developers
Classifier: Programming Language :: Python :: 3
Classifier: Programming Language :: Python :: 3 :: Only
Classifier: Topic :: Software Development
Classifier: Topic :: Utilities
Requires-Dist: aboutcode.hashid >= 0.2.0
Requires-Dist: packageurl_python >= 0.15.6
Requires-Dist: scancodeio >= 35.3.0
Project-URL: Homepage, https://github.com/aboutcode-org/purldb
